setup.py
bloomtime/__init__.py
bloomtime/bloomtime.py
bloomtime.egg-info/PKG-INFO
bloomtime.egg-info/SOURCES.txt
bloomtime.egg-info/dependency_links.txt
bloomtime.egg-info/not-zip-safe
bloomtime.egg-info/top_level.txt