Metadata-Version: 1.0
Name: bloomtime
Version: 0.3.0
Summary: Bloom filter with optional TTL
Home-page: https://github.com/Poogles/bloomtime
Author: Sam Pegler
Author-email: sam@sampegler.co.uk
License: MIT
Platform: UNKNOWN
